fab_addon_client/__init__.py
fab_addon_client/manager.py
fab_addon_client/models.py
fab_addon_client/version.py
fab_addon_client/views.py
fab_addon_client-0.0.1.dist-info/METADATA
fab_addon_client-0.0.1.dist-info/WHEEL
fab_addon_client-0.0.1.dist-info/top_level.txt
fab_addon_client-0.0.1.dist-info/RECORD
